


<?xml version = "1.0"?>
<!DOCTYPE ASTRO SYSTEM "http://vizier.u-strasbg.fr/xml/astrores.dtd">
<ASTRO ID="v0.8" xmlns:ASTRO="http://vizier.u-strasbg.fr/doc/astrores.htx">
  <TABLE ID="Table">
    <NAME>Fixed Targets</NAME>
    <TITLE>Fixed Targets for CFHT QSO</TITLE>
    <!-- Definition of each field -->
    <FIELD name="NAME" datatype="A" width="20">
        <DESCRIPTION>Name of target</DESCRIPTION>
    </FIELD>
    <FIELD name="RA"    datatype="A" width="11" unit="h"   format="RAh:RAm:RAs">
        <DESCRIPTION>Right ascension of target</DESCRIPTION>
    </FIELD>
    <FIELD name="DEC"   datatype="A" width="11" unit="deg" format="DEd:DEm:DEs">
        <DESCRIPTION>Declination of target</DESCRIPTION>
    </FIELD>
    <FIELD name="EPOCH" datatype="F" width="6">
        <DESCRIPTION>Epoch of coordinates</DESCRIPTION>
    </FIELD>
    <FIELD name="POINT" datatype="A" width="5">
        <DESCRIPTION>Pointing name</DESCRIPTION>
    </FIELD>
	<!-- Data table -->
<DATA><CSV headlines="4" colsep="|">
<![CDATA[
NAME                |RA         |DEC        |EPOCH |POINT|
                    |hh:mm:ss.ss|+dd:mm:ss.s|      |     |
12345678901234567890|12345678901|12345678901|123456|12345|
--------------------|-----------|-----------|------|-----|
Rho-Oph-01          |16:21:14.97|-24:33:48.7|2000.0|1    |
Rho-Oph-02          |16:21:15.69|-24:15:45.3|2000.0|1    |
Rho-Oph-03          |16:21:18.42|-23:59:14.5|2000.0|1    |
Rho-Oph-04          |16:21:19.84|-23:41:26.5|2000.0|1    |
Rho-Oph-05          |16:21:21.00|-23:24:33.6|2000.0|1    |
Rho-Oph-06          |16:21:21.35|-23:08:42.0|2000.0|1    |
Rho-Oph-07          |16:21:22.66|-22:53:44.6|2000.0|1    |
Rho-Oph-08          |16:22:25.73|-24:34:02.5|2000.0|1    |
Rho-Oph-09          |16:22:26.88|-24:16:10.4|2000.0|1    |
Rho-Oph-10          |16:22:29.35|-23:58:52.3|2000.0|1    |
Rho-Oph-11          |16:22:29.56|-23:41:11.5|2000.0|1    |
Rho-Oph-12          |16:22:31.79|-23:24:52.5|2000.0|1    |
Rho-Oph-13          |16:22:31.86|-22:53:44.5|2000.0|1    |
Rho-Oph-14          |16:22:31.94|-23:08:49.2|2000.0|1    |
Rho-Oph-15          |16:23:35.64|-24:34:34.7|2000.0|1    |
Rho-Oph-16          |16:23:36.82|-24:16:44.0|2000.0|1    |
Rho-Oph-17          |16:23:38.79|-23:58:57.1|2000.0|1    |
Rho-Oph-18          |16:23:39.74|-23:41:47.5|2000.0|1    |
Rho-Oph-19          |16:23:40.65|-23:25:11.2|2000.0|1    |
Rho-Oph-20          |16:23:41.32|-23:08:29.9|2000.0|1    |
Rho-Oph-21          |16:23:42.32|-22:54:00.0|2000.0|1    |
Rho-Oph-22          |16:24:47.44|-24:34:46.3|2000.0|1    |
Rho-Oph-23          |16:24:48.45|-24:16:51.9|2000.0|1    |
Rho-Oph-24          |16:24:49.45|-23:59:17.3|2000.0|1    |
Rho-Oph-25          |16:24:50.41|-23:42:10.2|2000.0|1    |
Rho-Oph-26          |16:24:50.77|-23:25:37.1|2000.0|1    |
Rho-Oph-27          |16:25:20.46|-24:51:25.6|2000.0|1    |
Rho-Oph-28          |16:25:44.10|-23:21:25.2|2000.0|1    |
Rho-Oph-29          |16:26:01.83|-24:35:11.2|2000.0|1    |
Rho-Oph-30          |16:26:02.70|-24:16:55.2|2000.0|1    |
Rho-Oph-31          |16:26:05.52|-23:59:28.4|2000.0|1    |
Rho-Oph-32          |16:27:15.53|-24:52:27.1|2000.0|1    |
Rho-Oph-33          |16:27:16.71|-24:35:45.8|2000.0|1    |
Rho-Oph-34          |16:27:17.98|-24:17:29.9|2000.0|1    |
Rho-Oph-35          |16:27:18.63|-23:59:55.1|2000.0|1    |
Rho-Oph-36          |16:28:28.19|-24:17:38.7|2000.0|1    |
Rho-Oph-37          |16:28:28.38|-24:52:51.1|2000.0|1    |
Rho-Oph-38          |16:28:28.84|-24:35:56.5|2000.0|1    |
Rho-Oph-39          |16:28:28.98|-24:00:10.4|2000.0|1    |
Rho-Oph-40          |16:29:45.28|-24:53:10.4|2000.0|1    |
Rho-Oph-41          |16:29:45.58|-24:36:11.9|2000.0|1    |
Rho-Oph-42          |16:29:45.89|-24:18:23.7|2000.0|1    |
Rho-Oph-43          |16:29:46.20|-24:00:35.5|2000.0|1    |
Rho-Oph-44          |16:31:00.14|-24:53:33.2|2000.0|1    |
Rho-Oph-45          |16:31:00.27|-24:36:24.7|2000.0|1    |
Rho-Oph-46          |16:31:01.13|-24:18:36.6|2000.0|1    |
Rho-Oph-47          |16:31:01.27|-24:00:40.4|2000.0|1    |
Rho-Oph-48          |16:31:36.21|-25:09:45.5|2000.0|1    |
Rho-Oph-49          |16:32:16.88|-24:53:21.6|2000.0|1    |
Rho-Oph-50          |16:32:17.72|-24:36:20.8|2000.0|1    |
Rho-Oph-51          |16:32:18.56|-24:18:29.9|2000.0|1    |
Rho-Oph-52          |16:32:19.24|-24:00:35.9|2000.0|1    |
Rho-Oph-53          |16:32:43.63|-25:09:41.9|2000.0|1    |
Rho-Oph-54          |16:33:34.31|-24:03:33.8|2000.0|1    |
Rho-Oph-55          |16:33:34.53|-24:21:13.7|2000.0|1    |
Rho-Oph-56          |16:33:35.02|-24:36:49.5|2000.0|1    |
Rho-Oph-57          |16:34:48.34|-24:41:27.5|2000.0|1    |
Rho-Oph-58          |16:34:49.53|-24:27:29.1|2000.0|1    |
Rho-Oph-59          |16:34:49.86|-24:09:14.9|2000.0|1    |
Rho-Oph-60          |16:36:09.02|-24:09:18.9|2000.0|1    |
Rho-Oph-61          |16:36:09.23|-24:27:09.2|2000.0|1    |
Rho-Oph-62          |16:37:25.21|-24:08:32.9|2000.0|1    |
Rho-Oph-63          |16:37:26.26|-24:26:48.2|2000.0|1    |
Rho-Oph-64          |16:38:41.89|-24:03:40.2|2000.0|1    |
Rho-Oph-65          |16:38:42.80|-24:21:22.9|2000.0|1    |
Rho-Oph-66          |16:39:55.31|-23:59:19.8|2000.0|1    |
Rho-Oph-67          |16:39:55.88|-24:17:06.2|2000.0|1    |
Rho-Oph-68          |16:41:12.39|-23:54:42.4|2000.0|1    |
Rho-Oph-69          |16:41:13.47|-24:09:35.6|2000.0|1    |
Rho-Oph-70          |16:42:25.32|-23:54:43.1|2000.0|1    |
Rho-Oph-71          |16:42:26.52|-24:09:30.8|2000.0|1    |
Rho-Oph-72          |16:43:52.79|-23:54:19.5|2000.0|1    |
Rho-Oph-73          |16:43:54.88|-24:09:11.0|2000.0|1    |
Rho-Oph-74          |16:45:04.56|-23:54:07.6|2000.0|1    |
Rho-Oph-75          |16:45:06.01|-24:08:20.8|2000.0|1    |
]]></CSV></DATA>
  </TABLE>
</ASTRO>
